README
setup.py
thread_pool/__init__.py
thread_pool/threadpool.py
thread_pool.egg-info/PKG-INFO
thread_pool.egg-info/SOURCES.txt
thread_pool.egg-info/dependency_links.txt
thread_pool.egg-info/top_level.txt