Metadata-Version: 1.0
Name: thread-pool
Version: 0.9
Summary: Implements thread pool with queue module of python.
Home-page: https://github.com/yummybian
Author: Yummy Bian
Author-email: yummy.bian#gmail.com
License: BSD
Keywords: thread pool
Platform: Any
Classifier: Development Status :: 4 - Beta
Classifier: Intended Audience :: Developers
Classifier: License :: OSI Approved :: BSD License
Classifier: Operating System :: OS Independent
Classifier: Programming Language :: Python
Classifier: Topic :: Software Development :: Libraries :: Python Modules
